myqcc-0.0.1.dist-info/licenses/LICENSE
qc/__init__.py
myqcc-0.0.1.dist-info/METADATA
myqcc-0.0.1.dist-info/WHEEL
myqcc-0.0.1.dist-info/top_level.txt
myqcc-0.0.1.dist-info/RECORD
