Metadata-Version: 2.4
Name: myqcc
Version: 0.0.1
Summary: A Qiskit package containing basic quantum circuits and gate implementations
Home-page: https://github.com/yourusername/myqcc
Author: QuantumDev
Author-email: quantum@example.com
Classifier: Programming Language :: Python :: 3
Classifier: License :: OSI Approved :: MIT License
Classifier: Operating System :: OS Independent
Requires-Python: >=3.6
License-File: LICENSE
Requires-Dist: qiskit
Requires-Dist: qiskit-aer
Requires-Dist: numpy
Requires-Dist: matplotlib
Dynamic: author
Dynamic: author-email
Dynamic: classifier
Dynamic: description
Dynamic: description-content-type
Dynamic: home-page
Dynamic: license-file
Dynamic: requires-dist
Dynamic: requires-python
Dynamic: summary
